src/__init__.py
src/database.py
src/models.py
src/server.py
mcp_server_aact_fastmcp-0.4.1.dist-info/METADATA
mcp_server_aact_fastmcp-0.4.1.dist-info/WHEEL
mcp_server_aact_fastmcp-0.4.1.dist-info/entry_points.txt
mcp_server_aact_fastmcp-0.4.1.dist-info/licenses/LICENSE
mcp_server_aact_fastmcp-0.4.1.dist-info/RECORD
